diraas/__init__.py
diraas/application.py
diraas/server.py
diraas-0.0.4.dist-info/DESCRIPTION.rst
diraas-0.0.4.dist-info/METADATA
diraas-0.0.4.dist-info/RECORD
diraas-0.0.4.dist-info/WHEEL
diraas-0.0.4.dist-info/entry_points.txt
diraas-0.0.4.dist-info/metadata.json
diraas-0.0.4.dist-info/top_level.txt
